JavaJichujiaochengCYuyanZhongwenwang/README.md
JavaJichujiaochengCYuyanZhongwenwang/__init__.py
JavaJichujiaochengCYuyanZhongwenwang/__main__.py
JavaJichujiaochengCYuyanZhongwenwang/file.epub
JavaJichujiaochengCYuyanZhongwenwang/index.html
JavaJichujiaochengCYuyanZhongwenwang/css/__init__.py
JavaJichujiaochengCYuyanZhongwenwang/css/annotations.css
JavaJichujiaochengCYuyanZhongwenwang/css/main.css
JavaJichujiaochengCYuyanZhongwenwang/css/normalize.css
JavaJichujiaochengCYuyanZhongwenwang/css/popup.css
JavaJichujiaochengCYuyanZhongwenwang/font/__init__.py
JavaJichujiaochengCYuyanZhongwenwang/font/fontello.eot
JavaJichujiaochengCYuyanZhongwenwang/font/fontello.svg
JavaJichujiaochengCYuyanZhongwenwang/font/fontello.ttf
JavaJichujiaochengCYuyanZhongwenwang/font/fontello.woff
JavaJichujiaochengCYuyanZhongwenwang/img/__init__.py
JavaJichujiaochengCYuyanZhongwenwang/img/annotator-glyph-sprite.png
JavaJichujiaochengCYuyanZhongwenwang/img/annotator-icon-sprite.png
JavaJichujiaochengCYuyanZhongwenwang/img/apple-touch-icon.png
JavaJichujiaochengCYuyanZhongwenwang/img/cancelfullscreen.png
JavaJichujiaochengCYuyanZhongwenwang/img/close.png
JavaJichujiaochengCYuyanZhongwenwang/img/fullscreen.png
JavaJichujiaochengCYuyanZhongwenwang/img/loader.gif
JavaJichujiaochengCYuyanZhongwenwang/img/menu-icon.png
JavaJichujiaochengCYuyanZhongwenwang/img/save.png
JavaJichujiaochengCYuyanZhongwenwang/img/saved.png
JavaJichujiaochengCYuyanZhongwenwang/img/settings-s.png
JavaJichujiaochengCYuyanZhongwenwang/img/settings.png
JavaJichujiaochengCYuyanZhongwenwang/img/star.png
JavaJichujiaochengCYuyanZhongwenwang/js/__init__.py
JavaJichujiaochengCYuyanZhongwenwang/js/epub.js
JavaJichujiaochengCYuyanZhongwenwang/js/epub.min.js
JavaJichujiaochengCYuyanZhongwenwang/js/epub.min.map
JavaJichujiaochengCYuyanZhongwenwang/js/hooks.min.js
JavaJichujiaochengCYuyanZhongwenwang/js/hooks.min.map
JavaJichujiaochengCYuyanZhongwenwang/js/reader.js
JavaJichujiaochengCYuyanZhongwenwang/js/reader.js.map
java_jichujiaocheng_c_yuyan_zhongwenwang-2024.3.4.0.dist-info/METADATA
java_jichujiaocheng_c_yuyan_zhongwenwang-2024.3.4.0.dist-info/WHEEL
java_jichujiaocheng_c_yuyan_zhongwenwang-2024.3.4.0.dist-info/entry_points.txt
java_jichujiaocheng_c_yuyan_zhongwenwang-2024.3.4.0.dist-info/top_level.txt
java_jichujiaocheng_c_yuyan_zhongwenwang-2024.3.4.0.dist-info/RECORD
